setup.py
mapmyfitness/__init__.py
mapmyfitness/constants.py
mapmyfitness/exceptions.py
mapmyfitness/inflators.py
mapmyfitness/paginator.py
mapmyfitness/serializers.py
mapmyfitness/timezones.py
mapmyfitness/utils.py
mapmyfitness.egg-info/PKG-INFO
mapmyfitness.egg-info/SOURCES.txt
mapmyfitness.egg-info/dependency_links.txt
mapmyfitness.egg-info/requires.txt
mapmyfitness.egg-info/top_level.txt
mapmyfitness/api/__init__.py
mapmyfitness/api/activity_type.py
mapmyfitness/api/base.py
mapmyfitness/api/config.py
mapmyfitness/api/mixins.py
mapmyfitness/api/route.py
mapmyfitness/api/user.py
mapmyfitness/api/workout.py
mapmyfitness/objects/__init__.py
mapmyfitness/objects/activity_type.py
mapmyfitness/objects/base.py
mapmyfitness/objects/route.py
mapmyfitness/objects/user.py
mapmyfitness/objects/workout.py
mapmyfitness/validators/__init__.py
mapmyfitness/validators/base.py
mapmyfitness/validators/route.py
mapmyfitness/validators/user.py
mapmyfitness/validators/workout.py