Metadata-Version: 1.0
Name: mapmyfitness
Version: 0.1.2
Summary: A python wrapper for the MapMyFitness API
Home-page: https://github.com/JasonSanford/mapmyfitness-python
Author: Jason Sanford
Author-email: jasonsanford@gmail.com
License: Apache License
Platform: UNKNOWN
